trentai/__init__.py
trentai/api_client.py
trentai/api_response.py
trentai/configuration.py
trentai/exceptions.py
trentai/py.typed
trentai/rest.py
trentai/api/__init__.py
trentai/api/prompt_firewall_api.py
trentai/models/__init__.py
trentai/models/error.py
trentai/models/prompt_firewall_request.py
trentai/models/prompt_firewall_response.py
trentai/models/prompt_firewall_response_rules_inner.py
trentai_sdk-0.0.3.dist-info/METADATA
trentai_sdk-0.0.3.dist-info/WHEEL
trentai_sdk-0.0.3.dist-info/top_level.txt
trentai_sdk-0.0.3.dist-info/RECORD
