Metadata-Version: 2.4
Name: trentai-sdk
Version: 0.0.3
Summary: trentai sdk
Home-page: 
Author: Brajesh Kumar
Author-email: brajesh@trent.ai
Keywords: OpenAPI,OpenAPI-Generator,trentai sdk
Requires-Dist: urllib3<2.1.0,>=1.25.3
Requires-Dist: python-dateutil
Requires-Dist: pydantic>=2
Requires-Dist: typing-extensions>=4.7.1
Dynamic: author
Dynamic: author-email
Dynamic: description
Dynamic: description-content-type
Dynamic: keywords
Dynamic: requires-dist
Dynamic: summary
